{
  "id": "uu-16-2017",
  "type": "statute",
  "title": "Penetapan Peraturan Pemerintah Pengganti Undang-undang Nomor 2 Tahun 2017 Tentang Perubahan Atas Undang-undang Nomor 17 Tahun 2013 Tentang Organisasi Kemasyarakatan Menjadi Undang-undang",
  "title_en": "",
  "short_name": "UU 16/2017",
  "status": "in_force",
  "issued_date": "",
  "in_force_date": "",
  "url": "https://peraturan.go.id/id/uu-no-16-tahun-2017",
  "description": "",
  "provisions": [
    {
      "provision_ref": "pasal0",
      "chapter": "Metadata",
      "section": "0",
      "title": "UU 16/2017 - Summary",
      "content": "Penetapan Peraturan Pemerintah Pengganti Undang-undang Nomor 2 Tahun 2017 Tentang Perubahan Atas Undang-undang Nomor 17 Tahun 2013 Tentang Organisasi Kemasyarakatan Menjadi Undang-undang\nType: UU No. 16 of 2017\nStatus: in_force\nSource: https://peraturan.go.id/id/uu-no-16-tahun-2017\nNote: Full text could not be fetched. This seed contains metadata only.\nRe-run ingestion when source is accessible for full Pasal text."
    }
  ],
  "definitions": []
}