{
  "id": "uu-2-1963",
  "type": "statute",
  "title": "Penetapan Peraturan Pemerintah Pengganti Undang-undang No. 12 Tahun 1962 Tentang Ketentuan Dibidang Fiskal Mengenai Pembayaran Sumbangan Wajib Istimewa (lembaran Negara Tahun 1962 No. 50) Menjadi Undang-undang",
  "title_en": "",
  "short_name": "UU 2/1963",
  "status": "in_force",
  "issued_date": "",
  "in_force_date": "",
  "url": "https://peraturan.go.id/id/uu-no-2-tahun-1963",
  "description": "",
  "provisions": [
    {
      "provision_ref": "pasal0",
      "chapter": "Metadata",
      "section": "0",
      "title": "UU 2/1963 - Summary",
      "content": "Penetapan Peraturan Pemerintah Pengganti Undang-undang No. 12 Tahun 1962 Tentang Ketentuan Dibidang Fiskal Mengenai Pembayaran Sumbangan Wajib Istimewa (lembaran Negara Tahun 1962 No. 50) Menjadi Undang-undang\nType: UU No. 2 of 1963\nStatus: in_force\nSource: https://peraturan.go.id/id/uu-no-2-tahun-1963\nNote: Full text could not be fetched. This seed contains metadata only.\nRe-run ingestion when source is accessible for full Pasal text."
    }
  ],
  "definitions": []
}