{
  "id": "uu-2-1995",
  "type": "statute",
  "title": "Anggaran Pendapatan dan Belanja Negara Tahun 1995/1996",
  "title_en": "",
  "short_name": "UU 2/1995",
  "status": "in_force",
  "issued_date": "",
  "in_force_date": "",
  "url": "https://peraturan.go.id/id/uu-no-2-tahun-1995",
  "description": "",
  "provisions": [
    {
      "provision_ref": "pasal0",
      "chapter": "Metadata",
      "section": "0",
      "title": "UU 2/1995 - Summary",
      "content": "Anggaran Pendapatan dan Belanja Negara Tahun 1995/1996\nType: UU No. 2 of 1995\nStatus: in_force\nSource: https://peraturan.go.id/id/uu-no-2-tahun-1995\nNote: Full text could not be fetched. This seed contains metadata only.\nRe-run ingestion when source is accessible for full Pasal text."
    }
  ],
  "definitions": []
}